<?xml version="1.0" encoding="UTF-8"?>
<comments>
<comment id="401431513" poolid="1" userhash="deadbeef" sendtime="1341930368">
	<text>　


キミ以上










　</text>
	<attr id="0" playtime="1" mode="1" fontsize="25" color="16751103"/>
</comment>
<comment id="541478094" poolid="1" userhash="deadbeef" sendtime="1341930368">
	<text>　


キミ以上　　　　　　　　　　　　










　</text>
	<attr id="0" playtime="3.2" mode="5" fontsize="25" color="16751103"/>
</comment>
<comment id="212593810" poolid="1" userhash="deadbeef" sendtime="1341930368">
	<text>　



ボク未満









　</text>
	<attr id="0" playtime="3.2" mode="1" fontsize="25" color="16764159"/>
</comment>
<comment id="1893616623" poolid="1" userhash="deadbeef" sendtime="1341930368">
	<text>　



ボク未満　　　　　　　　









　</text>
	<attr id="0" playtime="5.3" mode="1" fontsize="25" color="16764159"/>
</comment>
<comment id="1649089714" poolid="1" userhash="deadbeef" sendtime="1341930368">
	<text>　



ボク未満　　　　　　　　









　　</text>
	<attr id="0" playtime="5.3" mode="5" fontsize="25" color="16764159"/>
</comment>
<comment id="1371950290" poolid="1" userhash="deadbeef" sendtime="1341930368">
	<text>　




　


キミ以上　　　　　　　　　　　　










　</text>
	<attr id="0" playtime="6" mode="5" fontsize="25" color="16751103"/>
</comment>
<comment id="472785225" poolid="1" userhash="deadbeef" sendtime="1341930368">
	<text>　


キミ以上　　　　　　　　　　　　










　</text>
	<attr id="0" playtime="5.3" mode="5" fontsize="25" color="16751103"/>
</comment>
<comment id="1762326170" poolid="1" userhash="deadbeef" sendtime="1341930368">
	<text>　



　　ボク未満　　　　　　









　</text>
	<attr id="0" playtime="6.8" mode="5" fontsize="25" color="16751103"/>
</comment>
<comment id="1707734702" poolid="1" userhash="deadbeef" sendtime="1341930368">
	<text>　


每当你　　　　　　　　　　　　　










　</text>
	<attr id="0" playtime="14.7" mode="5" fontsize="25" color="16751103"/>
</comment>
<comment id="2091175190" poolid="1" userhash="deadbeef" sendtime="1341930368">
	<text>　


每当你　　　　　　　　　　　　　










　　</text>
	<attr id="0" playtime="17.1" mode="5" fontsize="25" color="16751103"/>
</comment>
<comment id="563393722" poolid="1" userhash="deadbeef" sendtime="1341930368">
	<text>　


笑起来的时候　　










　</text>
	<attr id="0" playtime="17.1" mode="1" fontsize="25" color="16764159"/>
</comment>
<comment id="112646675" poolid="1" userhash="deadbeef" sendtime="1341930368">
	<text>　


　　　笑起来的时候　　　　　　　










　</text>
	<attr id="0" playtime="18.6" mode="5" fontsize="25" color="16751103"/>
</comment>
<comment id="1629993853" poolid="1" userhash="deadbeef" sendtime="1341930368">
	<text>　






消失的上唇和眼睛






　</text>
	<attr id="0" playtime="21.6" mode="5" fontsize="25" color="16764159"/>
</comment>
<comment id="233159454" poolid="1" userhash="deadbeef" sendtime="1341930368">
	<text>　







消失的上唇和眼睛





　</text>
	<attr id="0" playtime="23.2" mode="5" fontsize="25" color="16764159"/>
</comment>
<comment id="557804261" poolid="1" userhash="deadbeef" sendtime="1341930368">
	<text>　






消失的上唇和眼睛






　</text>
	<attr id="0" playtime="23.2" mode="5" fontsize="25" color="16764159"/>
</comment>
<comment id="185059092" poolid="1" userhash="deadbeef" sendtime="1341930368">
	<text>　






上唇






　</text>
	<attr id="0" playtime="23.2" mode="5" fontsize="25" color="16751103"/>
</comment>
<comment id="75396" poolid="1" userhash="deadbeef" sendtime="1341930368">
	<text>　






　　　　　　眼睛






　</text>
	<attr id="0" playtime="25.4" mode="5" fontsize="25" color="0"/>
</comment>
<comment id="1673186513" poolid="1" userhash="deadbeef" sendtime="1341930368">
	<text>　





█████████
██
█████████





　</text>
	<attr id="0" playtime="22.9" mode="5" fontsize="25" color="16777215"/>
</comment>
<comment id="2053022477" poolid="1" userhash="deadbeef" sendtime="1341930368">
	<text>　





████████
██
████████





　</text>
	<attr id="0" playtime="22.9" mode="5" fontsize="25" color="16777215"/>
</comment>
<comment id="800672064" poolid="1" userhash="deadbeef" sendtime="1341930368">
	<text>　






消失　　　　　　






　</text>
	<attr id="0" playtime="22.9" mode="5" fontsize="25" color="16777215"/>
</comment>
<comment id="1129016296" poolid="1" userhash="deadbeef" sendtime="1341930368">
	<text>　







████████






　</text>
	<attr id="0" playtime="23.2" mode="5" fontsize="25" color="16777215"/>
</comment>
<comment id="910668818" poolid="1" userhash="deadbeef" sendtime="1341930368">
	<text>　






消失　　　　　　






　</text>
	<attr id="0" playtime="23.2" mode="5" fontsize="25" color="16777215"/>
</comment>
<comment id="953815832" poolid="1" userhash="deadbeef" sendtime="1341930368">
	<text>　







每当你哭泣的时候　　　　　　





　</text>
	<attr id="0" playtime="28.7" mode="5" fontsize="25" color="16764159"/>
</comment>
<comment id="1567926778" poolid="1" userhash="deadbeef" sendtime="1341930368">
	<text>　







每当　　　　　　　　　　　　





　</text>
	<attr id="0" playtime="28.9" mode="5" fontsize="25" color="16751103"/>
</comment>
<comment id="1860444600" poolid="1" userhash="deadbeef" sendtime="1341930368">
	<text>　







　　你　　　　　　　　　　　





　</text>
	<attr id="0" playtime="29.8" mode="5" fontsize="25" color="16751103"/>
</comment>
<comment id="1588203241" poolid="1" userhash="deadbeef" sendtime="1341930368">
	<text>　







每当　　　　　　　　　　　　





　</text>
	<attr id="0" playtime="29.8" mode="5" fontsize="25" color="16764159"/>
</comment>
<comment id="1383444356" poolid="1" userhash="deadbeef" sendtime="1341930368">
	<text>　







　　你　　的时候　　　　　　





　</text>
	<attr id="0" playtime="30.4" mode="5" fontsize="25" color="16764159"/>
</comment>
<comment id="992235341" poolid="1" userhash="deadbeef" sendtime="1341930368">
	<text>　







　　　哭泣　　　　　　　　　





　</text>
	<attr id="0" playtime="30.4" mode="5" fontsize="25" color="16751103"/>
</comment>
<comment id="67845768" poolid="1" userhash="deadbeef" sendtime="1341930368">
	<text>　







　　　　　的时候　　　　　　





　</text>
	<attr id="0" playtime="32.4" mode="5" fontsize="25" color="16751103"/>
</comment>
<comment id="585205877" poolid="1" userhash="deadbeef" sendtime="1341930368">
	<text>　







　　　哭泣　　　　　　　　　





　</text>
	<attr id="0" playtime="32.4" mode="5" fontsize="25" color="16764159"/>
</comment>
<comment id="852787147" poolid="1" userhash="deadbeef" sendtime="1341930368">
	<text>　




增加在　　　　　　　　　　








　</text>
	<attr id="0" playtime="35.6" mode="1" fontsize="25" color="16764159"/>
</comment>
<comment id="490091377" poolid="1" userhash="deadbeef" sendtime="1341930368">
	<text>　






脸颊上　　　　　






　</text>
	<attr id="0" playtime="35.6" mode="1" fontsize="25" color="16751103"/>
</comment>
<comment id="1147531499" poolid="1" userhash="deadbeef" sendtime="1341930368">
	<text>　








的温柔




　</text>
	<attr id="0" playtime="35.6" mode="1" fontsize="25" color="16738047"/>
</comment>
<comment id="1270613037" poolid="1" userhash="deadbeef" sendtime="1341930368">
	<text>　








温柔　　　　　　　　　　




　</text>
	<attr id="0" playtime="37.9" mode="5" fontsize="25" color="16738047"/>
</comment>
<comment id="1946896784" poolid="1" userhash="deadbeef" sendtime="1341930368">
	<text>　








模样　　　　　　




　</text>
	<attr id="0" playtime="38.2" mode="5" fontsize="25" color="16764159"/>
</comment>
<comment id="926554624" poolid="1" userhash="deadbeef" sendtime="1341930368">
	<text>　



「喜欢！」　　　　　　　　　









　</text>
	<attr id="0" playtime="42.1" mode="5" fontsize="25" color="16764159"/>
</comment>
<comment id="899625832" poolid="1" userhash="deadbeef" sendtime="1341930368">
	<text>　



　　　　　　　「很喜欢！！」









　</text>
	<attr id="0" playtime="42.1" mode="5" fontsize="25" color="16738047"/>
</comment>
<comment id="499158495" poolid="1" userhash="deadbeef" sendtime="1341930368">
	<text>　



「喜欢！」　　　　　　　　　









　</text>
	<attr id="0" playtime="43.8" mode="5" fontsize="37" color="16738047"/>
</comment>
<comment id="102453947" poolid="1" userhash="deadbeef" sendtime="1341930368">
	<text>　



　　　　　　　「很喜欢！！」




　</text>
	<attr id="0" playtime="43.8" mode="5" fontsize="37" color="16764159"/>
</comment>
<comment id="1721224602" poolid="1" userhash="deadbeef" sendtime="1341930368">
	<text>　



「超喜欢！！！」




　</text>
	<attr id="0" playtime="45.9" mode="1" fontsize="37" color="16724991"/>
</comment>
<comment id="473247732" poolid="1" userhash="deadbeef" sendtime="1341930368">
	<text>　







两人的吵闹~~　　　　　　　　





　</text>
	<attr id="0" playtime="47.3" mode="5" fontsize="25" color="16751103"/>
</comment>
<comment id="1966938242" poolid="1" userhash="deadbeef" sendtime="1341930368">
	<text>　



「看谁更喜欢谁」　　　　　　









　</text>
	<attr id="0" playtime="49" mode="5" fontsize="25" color="16764159"/>
</comment>
<comment id="1301595082" poolid="1" userhash="deadbeef" sendtime="1341930368">
	<text>　




　　　　　　今天就到此为止吧








　</text>
	<attr id="0" playtime="50.4" mode="5" fontsize="25" color="16751103"/>
</comment>
<comment id="1201859190" poolid="1" userhash="deadbeef" sendtime="1341930368">
	<text>　




　　　　　　今天就到此为止吧








　　</text>
	<attr id="0" playtime="52.3" mode="5" fontsize="25" color="16764108"/>
</comment>
<comment id="846411840" poolid="1" userhash="deadbeef" sendtime="1341930368">
	<text>　




　　　　　　今天就到此为止吧








　</text>
	<attr id="0" playtime="53.7" mode="5" fontsize="25" color="16738047"/>
</comment>
<comment id="1473658397" poolid="1" userhash="deadbeef" sendtime="1341930368">
	<text>　




　　　　　　今天就到此为止吧








　　</text>
	<attr id="0" playtime="55.2" mode="5" fontsize="25" color="16764159"/>
</comment>
<comment id="1211854608" poolid="1" userhash="deadbeef" sendtime="1341930368">
	<text>　





我无论在何　何　　　　　　　







　</text>
	<attr id="0" playtime="58.7" mode="5" fontsize="25" color="16764159"/>
</comment>
<comment id="1224083337" poolid="1" userhash="deadbeef" sendtime="1341930368">
	<text>　





　　　　　█　█　　　　　　







　</text>
	<attr id="0" playtime="58.7" mode="5" fontsize="25" color="16777215"/>
</comment>
<comment id="410108236" poolid="1" userhash="deadbeef" sendtime="1341930368">
	<text>　





　　　　　时　地　　　　　　







　</text>
	<attr id="0" playtime="58.7" mode="5" fontsize="25" color="16777113"/>
</comment>
<comment id="1111100234" poolid="1" userhash="deadbeef" sendtime="1341930368">
	<text>　




都








　</text>
	<attr id="0" playtime="62.9" mode="1" fontsize="25" color="16764159"/>
</comment>
<comment id="998953784" poolid="1" userhash="deadbeef" sendtime="1341930368">
	<text>　





　　　　喜







　</text>
	<attr id="0" playtime="62.9" mode="1" fontsize="25" color="16751103"/>
</comment>
<comment id="1248036157" poolid="1" userhash="deadbeef" sendtime="1341930368">
	<text>　






　　　　　　　　欢






　</text>
	<attr id="0" playtime="62.9" mode="1" fontsize="25" color="16751103"/>
</comment>
<comment id="447393557" poolid="1" userhash="deadbeef" sendtime="1341930368">
	<text>　







你





　</text>
	<attr id="0" playtime="62.9" mode="1" fontsize="25" color="16764159"/>
</comment>
<comment id="98843143" poolid="1" userhash="deadbeef" sendtime="1341930368">
	<text>　


所
以
说








　</text>
	<attr id="0" playtime="65.5" mode="5" fontsize="25" color="16738047"/>
</comment>
<comment id="1009059488" poolid="1" userhash="deadbeef" sendtime="1341930368">
	<text>　





无







　</text>
	<attr id="0" playtime="65.5" mode="1" fontsize="25" color="16764159"/>
</comment>
<comment id="1477476967" poolid="1" userhash="deadbeef" sendtime="1341930368">
	<text>　






论






　</text>
	<attr id="0" playtime="65.9" mode="1" fontsize="25" color="16764159"/>
</comment>
<comment id="1728971205" poolid="1" userhash="deadbeef" sendtime="1341930368">
	<text>　







何





　</text>
	<attr id="0" playtime="66.1" mode="1" fontsize="25" color="16751103"/>
</comment>
<comment id="1406477080" poolid="1" userhash="deadbeef" sendtime="1341930368">
	<text>　








时




　</text>
	<attr id="0" playtime="66.5" mode="1" fontsize="25" color="16751052"/>
</comment>
<comment id="1329797663" poolid="1" userhash="deadbeef" sendtime="1341930368">
	<text>　


所
以
说








　</text>
	<attr id="0" playtime="66.6" mode="5" fontsize="25" color="16738047"/>
</comment>
<comment id="1005884468" poolid="1" userhash="deadbeef" sendtime="1341930368">
	<text>　





无







　</text>
	<attr id="0" playtime="66.6" mode="5" fontsize="25" color="16764159"/>
</comment>
<comment id="2054346392" poolid="1" userhash="deadbeef" sendtime="1341930368">
	<text>　






论






　</text>
	<attr id="0" playtime="67" mode="5" fontsize="25" color="16764159"/>
</comment>
<comment id="1910887000" poolid="1" userhash="deadbeef" sendtime="1341930368">
	<text>　







何





　</text>
	<attr id="0" playtime="67.3" mode="5" fontsize="25" color="16751103"/>
</comment>
<comment id="896685232" poolid="1" userhash="deadbeef" sendtime="1341930368">
	<text>　








时




　</text>
	<attr id="0" playtime="67.6" mode="5" fontsize="25" color="16751052"/>
</comment>
<comment id="1002547493" poolid="1" userhash="deadbeef" sendtime="1341930368">
	<text>　










都会打翻　　　醋坛子　　　　　　


　</text>
	<attr id="0" playtime="68.3" mode="5" fontsize="25" color="16751103"/>
</comment>
<comment id="390902589" poolid="1" userhash="deadbeef" sendtime="1341930368">
	<text>　










　　　　美味的　　　　　　　　　


　</text>
	<attr id="0" playtime="68.3" mode="5" fontsize="25" color="16724940"/>
</comment>
<comment id="2515862" poolid="1" userhash="deadbeef" sendtime="1341930368">
	<text>　










　　　　美味的　　　　　　　　　


　　</text>
	<attr id="0" playtime="68.9" mode="5" fontsize="25" color="16751103"/>
</comment>
<comment id="1006895365" poolid="1" userhash="deadbeef" sendtime="1341930368">
	<text>　










　　　　美味的　　　　　　　　　


　</text>
	<attr id="0" playtime="69.2" mode="5" fontsize="25" color="16724940"/>
</comment>
<comment id="676587675" poolid="1" userhash="deadbeef" sendtime="1341930368">
	<text>　











　　　　　　　　　　　desu~desu~

　</text>
	<attr id="0" playtime="71" mode="5" fontsize="25" color="16751103"/>
</comment>
<comment id="274462277" poolid="1" userhash="deadbeef" sendtime="1341930368">
	<text>　











　　　　　　　　　　　desu~desu~

　　</text>
	<attr id="0" playtime="71" mode="4" fontsize="25" color="16764108"/>
</comment>
<comment id="792317026" poolid="1" userhash="deadbeef" sendtime="1341930368">
	<text>　





比你　　　　　　　　　　　　　　







　</text>
	<attr id="0" playtime="86.4" mode="5" fontsize="25" color="16751103"/>
</comment>
<comment id="614685685" poolid="1" userhash="deadbeef" sendtime="1341930368">
	<text>　






更可爱






　</text>
	<attr id="0" playtime="86.4" mode="1" fontsize="25" color="16764159"/>
</comment>
<comment id="1686084066" poolid="1" userhash="deadbeef" sendtime="1341930368">
	<text>　





比你　　　　　　　　　　　　　　







　</text>
	<attr id="0" playtime="89.2" mode="5" fontsize="25" color="16751103"/>
</comment>
<comment id="36112566" poolid="1" userhash="deadbeef" sendtime="1341930368">
	<text>　







更温柔





　</text>
	<attr id="0" playtime="89.8" mode="1" fontsize="25" color="16764057"/>
</comment>
<comment id="1570771695" poolid="1" userhash="deadbeef" sendtime="1341930368">
	<text>　





比你　　　　　　　　　　　　　　







　</text>
	<attr id="0" playtime="91.2" mode="5" fontsize="25" color="16751103"/>
</comment>
<comment id="2030393436" poolid="1" userhash="deadbeef" sendtime="1341930368">
	<text>　





比你　　　　　　　　　　　　　　







　　</text>
	<attr id="0" playtime="94" mode="5" fontsize="25" color="16751103"/>
</comment>
<comment id="486313754" poolid="1" userhash="deadbeef" sendtime="1341930368">
	<text>　








胸襟更广阔的　　




　</text>
	<attr id="0" playtime="94" mode="1" fontsize="25" color="10053375"/>
</comment>
<comment id="1256693927" poolid="1" userhash="deadbeef" sendtime="1341930368">
	<text>　








　　　　　　女孩




　</text>
	<attr id="0" playtime="94" mode="1" fontsize="25" color="16751103"/>
</comment>
<comment id="1701617893" poolid="1" userhash="deadbeef" sendtime="1341930368">
	<text>　



哼—！　　　　　　　　　









　</text>
	<attr id="0" playtime="98.5" mode="5" fontsize="25" color="16751103"/>
</comment>
<comment id="1319694852" poolid="1" userhash="deadbeef" sendtime="1341930368">
	<text>　



　　　嘭嘭☆　　　　









　</text>
	<attr id="0" playtime="98.5" mode="5" fontsize="25" color="16764057"/>
</comment>
<comment id="1432334876" poolid="1" userhash="deadbeef" sendtime="1341930368">
	<text>　



　　　　　　　嘭嘭☆









　</text>
	<attr id="0" playtime="98.7" mode="5" fontsize="25" color="16764057"/>
</comment>
<comment id="481926211" poolid="1" userhash="deadbeef" sendtime="1341930368">
	<text>　






你虽然不是这　　的全部　　　　　






　</text>
	<attr id="0" playtime="100.1" mode="5" fontsize="25" color="10053324"/>
</comment>
<comment id="821189464" poolid="1" userhash="deadbeef" sendtime="1341930368">
	<text>　






世界　　　　　　　　　






　</text>
	<attr id="0" playtime="100.1" mode="1" fontsize="25" color="13408767"/>
</comment>
<comment id="961964977" poolid="1" userhash="deadbeef" sendtime="1341930368">
	<text>　






　　　　　　世界　　　　　　　　






　</text>
	<attr id="0" playtime="101.2" mode="5" fontsize="25" color="13408767"/>
</comment>
<comment id="760811122" poolid="1" userhash="deadbeef" sendtime="1341930368">
	<text>　






　　　　是这世界的　　　　　　　






　</text>
	<attr id="0" playtime="102.2" mode="5" fontsize="25" color="13408767"/>
</comment>
<comment id="251539660" poolid="1" userhash="deadbeef" sendtime="1341930368">
	<text>　






你虽然不　　　　　全部　　　　　






　</text>
	<attr id="0" playtime="102.2" mode="5" fontsize="25" color="10053375"/>
</comment>
<comment id="1752439853" poolid="1" userhash="deadbeef" sendtime="1341930368">
	<text>　






　　然不是这世界的全　　　　　　






　</text>
	<attr id="0" playtime="103.3" mode="5" fontsize="25" color="13408767"/>
</comment>
<comment id="1211416349" poolid="1" userhash="deadbeef" sendtime="1341930368">
	<text>　






你虽然不是这世界的全部　　　　　






　</text>
	<attr id="0" playtime="104.3" mode="5" fontsize="25" color="13408767"/>
</comment>
<comment id="158163470" poolid="1" userhash="deadbeef" sendtime="1341930368">
	<text>　









但是我心里却只有　一个



　</text>
	<attr id="0" playtime="106.4" mode="1" fontsize="25" color="16764159"/>
</comment>
<comment id="1350240683" poolid="1" userhash="deadbeef" sendtime="1341930368">
	<text>　









　　　　　　　　你　　



　</text>
	<attr id="0" playtime="107.9" mode="1" fontsize="25" color="16738047"/>
</comment>
<comment id="313404497" poolid="1" userhash="deadbeef" sendtime="1341930368">
	<text>　









　　　　　　　　你　　



　　</text>
	<attr id="0" playtime="107.9" mode="5" fontsize="25" color="16724991"/>
</comment>
<comment id="390003389" poolid="1" userhash="deadbeef" sendtime="1341930368">
	<text>　







　　　　　♡♡　♡♡　
　　　　♡♡♡♡♡♡♡
　　　　♡♡♡　♡♡♡
　　　　　♡♡♡♡♡　


　</text>
	<attr id="0" playtime="111.2" mode="5" fontsize="25" color="16751103"/>
</comment>
<comment id="771997561" poolid="1" userhash="deadbeef" sendtime="1341930368">
	<text>　





我们俩无论　　　　







　</text>
	<attr id="0" playtime="116.9" mode="1" fontsize="25" color="16751103"/>
</comment>
<comment id="1437895382" poolid="1" userhash="deadbeef" sendtime="1341930368">
	<text>　





　　　　　　█　█







　</text>
	<attr id="0" playtime="116.9" mode="1" fontsize="25" color="16777215"/>
</comment>
<comment id="1448308736" poolid="1" userhash="deadbeef" sendtime="1341930368">
	<text>　





　　　　　何　何　







　</text>
	<attr id="0" playtime="116.9" mode="1" fontsize="25" color="16764159"/>
</comment>
<comment id="1049608744" poolid="1" userhash="deadbeef" sendtime="1341930368">
	<text>　





　　　　　　时　地







　</text>
	<attr id="0" playtime="116.9" mode="1" fontsize="25" color="16777113"/>
</comment>
<comment id="1103538098" poolid="1" userhash="deadbeef" sendtime="1341930368">
	<text>　







都会在　　　　　





　</text>
	<attr id="0" playtime="119.4" mode="5" fontsize="25" color="16751103"/>
</comment>
<comment id="2052227444" poolid="1" userhash="deadbeef" sendtime="1341930368">
	<text>　







　　　一起　　　





　</text>
	<attr id="0" playtime="120" mode="5" fontsize="25" color="10053375"/>
</comment>
<comment id="575666464" poolid="1" userhash="deadbeef" sendtime="1341930368">
	<text>　







　　　　　♡　　





　</text>
	<attr id="0" playtime="120" mode="5" fontsize="25" color="16764159"/>
</comment>
<comment id="1074039618" poolid="1" userhash="deadbeef" sendtime="1341930368">
	<text>　



所
以
说







　　　　　　　　　　　　</text>
	<attr id="0" playtime="123.6" mode="5" fontsize="25" color="16751103"/>
</comment>
<comment id="1472068358" poolid="1" userhash="deadbeef" sendtime="1341930368">
	<text>　






无论　






　</text>
	<attr id="0" playtime="123.6" mode="1" fontsize="25" color="16738047"/>
</comment>
<comment id="1037519647" poolid="1" userhash="deadbeef" sendtime="1341930368">
	<text>　







　　　　　何时





　</text>
	<attr id="0" playtime="123.6" mode="1" fontsize="25" color="16751103"/>
</comment>
<comment id="1304438386" poolid="1" userhash="deadbeef" sendtime="1341930368">
	<text>　








　　　　　　　　　　　　都可以放心　　




　</text>
	<attr id="0" playtime="123.6" mode="1" fontsize="25" color="13408767"/>
</comment>
<comment id="187581986" poolid="1" userhash="deadbeef" sendtime="1341930368">
	<text>　








　　　　　　　　　　　　　　　　　哭泣




　</text>
	<attr id="0" playtime="123.6" mode="1" fontsize="25" color="13421823"/>
</comment>
<comment id="1196360271" poolid="1" userhash="deadbeef" sendtime="1341930368">
	<text>　








　　　　　　　没什么好怕的♡




　</text>
	<attr id="0" playtime="126.3" mode="5" fontsize="25" color="10053375"/>
</comment>
</comments>
